rpc_reader/__init__.py
rpc_reader/rpc_reader.py
rpc_reader/lib/__init__.py
rpc_reader/lib/print_progressbar.py
rpc_reader-0.9.dist-info/LICENSE
rpc_reader-0.9.dist-info/METADATA
rpc_reader-0.9.dist-info/WHEEL
rpc_reader-0.9.dist-info/entry_points.txt
rpc_reader-0.9.dist-info/top_level.txt
rpc_reader-0.9.dist-info/RECORD
