Metadata-Version: 2.1
Name: rpc-reader
Version: 0.9
Summary: Application to read MTS PRC3 files
Home-page: https://gitlab.com/t8237/rpc_reader
Author: Niklas Melin
Author-email: niklas.melin@scania.com
License: UNKNOWN
Platform: UNKNOWN
Classifier: Development Status :: 4 - Beta
Classifier: Programming Language :: Python :: 3
Classifier: License :: OSI Approved :: MIT License
Classifier: Operating System :: OS Independent
Requires-Python: >=3.7
License-File: LICENSE
Requires-Dist: setuptools
Requires-Dist: wheel
Requires-Dist: numpy
